{
  "$type": "Comindware.Platform.Contracts.Desktop.IndicatorWidgetConfigModel, Comindware.Platform.Contracts",
  "AggregationMethod": "Value",
  "AllowDrillDown": false,
  "Children": {
    "$type": "System.Collections.Generic.List`1[[Comindware.Platform.Contracts.Desktop.WidgetConfigModel, Comindware.Platform.Contracts]], mscorlib",
    "$values": [
      {
        "$type": "Comindware.Platform.Contracts.Desktop.IconWidgetConfigModel, Comindware.Platform.Contracts",
        "Color": "#ff0000",
        "GlobalAlias": {
          "$type": "Comindware.Platform.Contracts.GlobalAlias, Comindware.Platform.Contracts",
          "Alias": "WidgetConfig_352dc46c-a9aa-42f0-afab-36ecf5ad6ad4",
          "Owner": "WidgetConfig_ba1d13c9-7b11-4faa-8cfc-e43902090ff0",
          "Solution": "",
          "Type": "DesktopWidgetConfig"
        },
        "IconType": "Undefined",
        "Name": "Изображение",
        "Order": 1,
        "PropertyPath": {
          "$type": "Comindware.Platform.Contracts.GlobalAlias[], Comindware.Platform.Contracts",
          "$values": []
        },
        "Template": {
          "$type": "Comindware.Platform.Contracts.GlobalAlias, Comindware.Platform.Contracts",
          "Alias": "Должность",
          "Solution": "Управлениекомандировками",
          "Type": "RecordTemplate"
        },
        "Type": "Icon"
      }
    ]
  },
  "FieldType": "Indicator",
  "GlobalAlias": {
    "$type": "Comindware.Platform.Contracts.GlobalAlias, Comindware.Platform.Contracts",
    "Alias": "WidgetConfig_ba1d13c9-7b11-4faa-8cfc-e43902090ff0",
    "Owner": "Управлениекомандировками",
    "Solution": "",
    "Type": "DesktopWidgetConfig"
  },
  "Label": {
    "$type": "Comindware.Platform.Contracts.Desktop.Label, Comindware.Platform.Contracts",
    "Alignment": "Undefined",
    "Hidden": false,
    "Text": "мяф"
  },
  "Name": "Что-то",
  "Order": 0,
  "PropertyPath": {
    "$type": "Comindware.Platform.Contracts.GlobalAlias[], Comindware.Platform.Contracts",
    "$values": []
  },
  "Template": {
    "$type": "Comindware.Platform.Contracts.GlobalAlias, Comindware.Platform.Contracts",
    "Alias": "Должность",
    "Solution": "Управлениекомандировками",
    "Type": "RecordTemplate"
  },
  "Type": "FieldComponent"
}